README.rst
setup.py
moses/__init__.py
moses/__main__.py
moses/client.py
moses/cmd.py
moses/defaults.py
moses/io.py
moses/log.py
moses/misc.py
moses/server.py
moses/socks.py
moses/version.py
moses.egg-info/PKG-INFO
moses.egg-info/SOURCES.txt
moses.egg-info/dependency_links.txt
moses.egg-info/entry_points.txt
moses.egg-info/not-zip-safe
moses.egg-info/requires.txt
moses.egg-info/top_level.txt
moses/staff/__init__.py
moses/staff/__main__.py
moses/staff/cmd.py
moses/staff/dns.py
moses/staff/tcp.py
moses/tests/__init__.py
moses/tests/dummy.py
moses/tests/test_io.py
moses/tests/test_misc.py
moses/tests/test_socks.py