Metadata-Version: 1.1
Name: moses
Version: 0.10.0
Summary: TLS encrypted socks5 proxy
Home-page: https://github.com/l04m33/moses
Author: Kay Zheng
Author-email: l04m33@gmail.com
License: MIT
Keywords: socks,proxy
Platform: UNKNOWN
Classifier: License :: OSI Approved :: MIT License
Classifier: Programming Language :: Python :: 3.4
